community_learning/__init__.py
community_learning/_nbdev.py
community_learning/data.py
community_learning-0.0.2.dist-info/LICENSE
community_learning-0.0.2.dist-info/METADATA
community_learning-0.0.2.dist-info/WHEEL
community_learning-0.0.2.dist-info/entry_points.txt
community_learning-0.0.2.dist-info/top_level.txt
community_learning-0.0.2.dist-info/RECORD
